dash_down/__init__.py
dash_down/class_names.py
dash_down/directives.py
dash_down/express.py
dash_down/html_renderer.py
dash_down/mantine_renderer.py
dash_down/plugins.py
dash_down-0.2.0.dist-info/licenses/LICENSE
dash_down-0.2.0.dist-info/METADATA
dash_down-0.2.0.dist-info/WHEEL
dash_down-0.2.0.dist-info/top_level.txt
dash_down-0.2.0.dist-info/RECORD
