Metadata-Version: 2.4
Name: dash-down
Version: 0.2.0
Summary: Render markdown as Plotly Dash components.
Author-email: emher <emil.h.eriksen@gmail.com>
License-Expression: MIT
Project-URL: homepage, https://github.com/emilhe/dash-down
Project-URL: repository, https://github.com/emilhe/dash-down
Requires-Python: >=3.12
License-File: LICENSE
Requires-Dist: dash>=3.0.0
Requires-Dist: dash-extensions>=2.0.0
Requires-Dist: dash-mantine-components>=1.0.0
Requires-Dist: dash-iconify>=0.1.2
Requires-Dist: mistune==2.0.4
Requires-Dist: dataclass-wizard>=0.30.1
Dynamic: license-file
